subsceneAPI/__init__.py
subsceneAPI/cli.py
subsceneAPI/subtitle.py
subsceneAPI-0.2.dist-info/LICENSE
subsceneAPI-0.2.dist-info/METADATA
subsceneAPI-0.2.dist-info/WHEEL
subsceneAPI-0.2.dist-info/entry_points.txt
subsceneAPI-0.2.dist-info/top_level.txt
subsceneAPI-0.2.dist-info/RECORD
